vinyl/__init__.py
vinyl/chart.py
vinyl/connect.py
vinyl/constructors.py
vinyl/examples.py
vinyl/operations.py
vinyl/cli/__init__.py
vinyl/cli/dbt.py
vinyl/cli/events.py
vinyl/cli/main.py
vinyl/cli/preview.py
vinyl/cli/project.py
vinyl/cli/sources.py
vinyl/cli/user.py
vinyl/cli/_project_scaffolding/README.md
vinyl/cli/_project_scaffolding/__project_name__/__init__.py
vinyl/cli/_project_scaffolding/__project_name__/resources.py
vinyl/cli/_project_scaffolding/__project_name__/data/holidays_events.csv
vinyl/cli/_project_scaffolding/__project_name__/data/store_num_transactions.csv
vinyl/cli/_project_scaffolding/__project_name__/data/stores.csv
vinyl/cli/_project_scaffolding/__project_name__/models/__init__.py
vinyl/cli/_project_scaffolding/__project_name__/models/models.py
vinyl/cli/_project_scaffolding/__project_name__/sources/__init__.py
vinyl/data/airports.parquet
vinyl/data/anscombe.parquet
vinyl/data/barley.parquet
vinyl/data/birdstrikes.parquet
vinyl/data/budget.parquet
vinyl/data/budgets.parquet
vinyl/data/burtin.parquet
vinyl/data/cars.parquet
vinyl/data/climate.parquet
vinyl/data/co2_concentration.parquet
vinyl/data/countries.parquet
vinyl/data/crimea.parquet
vinyl/data/disasters.parquet
vinyl/data/driving.parquet
vinyl/data/flare.parquet
vinyl/data/flare_dependencies.parquet
vinyl/data/flights_10k.parquet
vinyl/data/flights_200k.parquet
vinyl/data/flights_20k.parquet
vinyl/data/flights_2k.parquet
vinyl/data/flights_3m.parquet
vinyl/data/flights_5k.parquet
vinyl/data/flights_airport.parquet
vinyl/data/gapminder.parquet
vinyl/data/gapminder_health_income.parquet
vinyl/data/github.parquet
vinyl/data/income.parquet
vinyl/data/iowa_electricity.parquet
vinyl/data/iris.parquet
vinyl/data/jobs.parquet
vinyl/data/la_riots.parquet
vinyl/data/londonCentroids.parquet
vinyl/data/lookup_groups.parquet
vinyl/data/lookup_people.parquet
vinyl/data/monarchs.parquet
vinyl/data/normal_2d.parquet
vinyl/data/obesity.parquet
vinyl/data/ohlc.parquet
vinyl/data/points.parquet
vinyl-0.0.26.dist-info/METADATA
vinyl-0.0.26.dist-info/WHEEL
vinyl-0.0.26.dist-info/entry_points.txt
vinyl-0.0.26.dist-info/licenses/LICENSE
vinyl-0.0.26.dist-info/RECORD
