Metadata-Version: 2.3
Name: vinyl
Version: 0.0.26
Summary: Python backend for Notebook
Author-email: Ian Tracey <ian@turntable.so>, Justin Leder <justin@turntable.so>
License-File: LICENSE
Requires-Python: <3.12,>=3.11
Requires-Dist: bidict>=0.23.1
Requires-Dist: cryptography>=42.0.8
Requires-Dist: dbt-extractor>=0.5.1
Requires-Dist: deepmerge>=1.1.1
Requires-Dist: fastapi>=0.111.0
Requires-Dist: fsspec>=2024.6.1
Requires-Dist: geopandas>=1.0.0
Requires-Dist: httpx>=0.27.0
Requires-Dist: lets-plot>=4.3.3
Requires-Dist: mpire[dill]>=2.10.2
Requires-Dist: netext>=0.2.1
Requires-Dist: ngrok>=1.3.0
Requires-Dist: orjson>=3.10.5
Requires-Dist: pandas>=2.2.2
Requires-Dist: platformdirs>=4.2.2
Requires-Dist: posthog>=3.5.0
Requires-Dist: pydantic>=2.7.4
Requires-Dist: python-dotenv>=1.0.1
Requires-Dist: ruff>=0.5.0
Requires-Dist: rustworkx>=0.15.0
Requires-Dist: sqlglot[rs]>=23.4
Requires-Dist: textual>=0.70.0
Requires-Dist: toml>=0.10.2
Requires-Dist: tqdm>=4.66.4
Requires-Dist: turntable-spoonbill[bigquery,duckdb,postgres,snowflake]>=10.0.2
Requires-Dist: typer>=0.12.3
Requires-Dist: uvicorn>=0.30.1
Requires-Dist: watchdog[watchmedo]>=4.0.1
Requires-Dist: websockets>=10.0
